[
  {
    "type": "price_drop",
    "product_name": "Earl Baker - Whole Flower - Midnight O 0106 (H) (3.5g)",
    "brand": "Earl Baker",
    "message": "Earl Baker Earl Baker - Whole Flower - Midnight O 0106 (H) (3.5g): $59.00 > $47.20"
  },
  {
    "type": "price_drop",
    "product_name": "Earl Baker - Whole Flower - Peach Diesel 0104 (S) (3.5g)",
    "brand": "Earl Baker",
    "message": "Earl Baker Earl Baker - Whole Flower - Peach Diesel 0104 (S) (3.5g): $58.00 > $46.40"
  },
  {
    "type": "price_drop",
    "product_name": "Earl Baker - Whole Flower - Bad Decisions 0103 (H) (3.5g)",
    "brand": "Earl Baker",
    "message": "Earl Baker Earl Baker - Whole Flower - Bad Decisions 0103 (H) (3.5g): $58.00 > $46.40"
  },
  {
    "type": "price_drop",
    "product_name": "Earl Baker - Whole Flower .5g x 2 Preroll - Chem Pop 021 (2pk)",
    "brand": "Earl Baker",
    "message": "Earl Baker Earl Baker - Whole Flower .5g x 2 Preroll - Chem Pop 021 (2pk): $13.00 > $10.40"
  },
  {
    "type": "price_drop",
    "product_name": "Earl Baker - Whole Flower -Suga T's 0102 (H)(3.5g)",
    "brand": "Earl Baker",
    "message": "Earl Baker Earl Baker - Whole Flower -Suga T's 0102 (H)(3.5g): $48.00 > $38.40"
  },
  {
    "type": "price_drop",
    "product_name": "Earl Baker - Whole Flower - Super Silver Grapefruit 0105 (S) (3.5g)",
    "brand": "Earl Baker",
    "message": "Earl Baker Earl Baker - Whole Flower - Super Silver Grapefruit 0105 (S) (3.5g): $58.00 > $46.40"
  },
  {
    "type": "price_drop",
    "product_name": "Earl Baker - Whole Flower - Next level 0108(3.5g)(H)",
    "brand": "Earl Baker",
    "message": "Earl Baker Earl Baker - Whole Flower - Next level 0108(3.5g)(H): $58.00 > $46.40"
  }
]