[
  {
    "type": "out_of_stock",
    "product_name": "Asteroid GalaxEats Gummies Sour Green Apple (S) T99.8mg - C0170000035",
    "brand": "Asteroid Galaxeats",
    "message": "Gone: Asteroid Galaxeats - Asteroid GalaxEats Gummies Sour Green Apple (S) T99.8mg - C0170000035"
  },
  {
    "type": "out_of_stock",
    "product_name": "Awssom Pre-Roll BFG 00059",
    "brand": "Awssom",
    "message": "Gone: Awssom - Awssom Pre-Roll BFG 00059"
  },
  {
    "type": "out_of_stock",
    "product_name": "OGKB Stomper Live Resin Vape T364 H 25840",
    "brand": "CTPharma",
    "message": "Gone: CTPharma - OGKB Stomper Live Resin Vape T364 H 25840"
  },
  {
    "type": "out_of_stock",
    "product_name": "Carbon FBR PR 41727",
    "brand": "Theraplant",
    "message": "Gone: Theraplant - Carbon FBR PR 41727"
  },
  {
    "type": "out_of_stock",
    "product_name": "Wana Sativa Mango 00263",
    "brand": "Wana",
    "message": "Gone: Wana - Wana Sativa Mango 00263"
  },
  {
    "type": "out_of_stock",
    "product_name": "Wana Quick Hybrid Limoncello Fast-Acting Gummies 00331",
    "brand": "Wana",
    "message": "Gone: Wana - Wana Quick Hybrid Limoncello Fast-Acting Gummies 00331"
  },
  {
    "type": "out_of_stock",
    "product_name": "Select Legacy Series Briq 2.0 Blue Dream (H) 01489",
    "brand": "Select",
    "message": "Gone: Select - Select Legacy Series Briq 2.0 Blue Dream (H) 01489"
  }
]